lora_utils/__init__.py
lora_utils/util.py
lora_utils-0.1.1.dist-info/LICENSE
lora_utils-0.1.1.dist-info/METADATA
lora_utils-0.1.1.dist-info/WHEEL
lora_utils-0.1.1.dist-info/RECORD
