Metadata-Version: 2.1
Name: lora-utils
Version: 0.1.1
Summary: 
License: MPL-2.0
Author: Magenta ApS
Author-email: info@magenta.dk
Requires-Python: >=3.8,<4.0
Classifier: License :: OSI Approved
Classifier: Programming Language :: Python :: 3
Classifier: Programming Language :: Python :: 3.8
Classifier: Programming Language :: Python :: 3.9
Classifier: Programming Language :: Python :: 3.10
Classifier: Programming Language :: Python :: 3.11
Requires-Dist: python-dateutil (>=2.8.2,<3.0.0)
